whist_backend/__init__.py
whist_backend/bet.py
whist_backend/cards.py
whist_backend/event_listener_protocol.py
whist_backend/player_strategy_protocol.py
whist_backend/py.typed
whist_backend/round_simulator.py
whist_backend-0.2.3.dist-info/LICENSE
whist_backend-0.2.3.dist-info/METADATA
whist_backend-0.2.3.dist-info/WHEEL
whist_backend-0.2.3.dist-info/top_level.txt
whist_backend-0.2.3.dist-info/RECORD
