Metadata-Version: 2.1
Name: whist_backend
Version: 0.2.3
Summary: Play rounds of whist (with bots or real players).
Requires-Python: >=3.9.0
License-File: LICENSE
